dovecot_archive.py
dovecot_archive-1.1.0.dist-info/LICENSE
dovecot_archive-1.1.0.dist-info/METADATA
dovecot_archive-1.1.0.dist-info/WHEEL
dovecot_archive-1.1.0.dist-info/entry_points.txt
dovecot_archive-1.1.0.dist-info/top_level.txt
dovecot_archive-1.1.0.dist-info/RECORD
