Metadata-Version: 2.1
Name: dovecot-archive
Version: 1.1.0
Summary: A doveadm wrapper for common archival tasks.
Home-page: https://github.com/Disassembler0/dovecot-archive
Author: Disassembler
Author-email: disassembler@dasm.cz
License: BSD-3-Clause
Platform: UNKNOWN
Classifier: Development Status :: 5 - Production/Stable
Classifier: Environment :: Console
Classifier: Intended Audience :: System Administrators
Classifier: License :: OSI Approved :: BSD License
Classifier: Operating System :: POSIX
Classifier: Programming Language :: Python :: 3.5
Classifier: Programming Language :: Python :: 3.6
Classifier: Programming Language :: Python :: 3.7
Classifier: Programming Language :: Python :: 3.8
Classifier: Programming Language :: Python :: 3.9
Classifier: Topic :: Communications :: Email
Classifier: Topic :: Communications :: Email :: Post-Office
Classifier: Topic :: System :: Archiving
Classifier: Topic :: System :: Systems Administration
Requires-Python: >=3.5
Requires-Dist: python-dateutil
